simpletestok/__init__.py
simpletestok/main.py
simpletestok/module1.py
simpletestok-0.1.0.dist-info/METADATA
simpletestok-0.1.0.dist-info/WHEEL
simpletestok-0.1.0.dist-info/top_level.txt
simpletestok-0.1.0.dist-info/RECORD
